brle/__init__.py
brle_python-0.1.0.dist-info/LICENSE
brle_python-0.1.0.dist-info/METADATA
brle_python-0.1.0.dist-info/WHEEL
brle_python-0.1.0.dist-info/RECORD
